{
"type": "FeatureCollection",
"name": "Point_Jaringan_Airminum",
"crs": { "type": "name", "properties": { "name": "urn:ogc:def:crs:OGC:1.3:CRS84" } },
"features": [
{ "type": "Feature", "properties": { "OBJECTID": 1, "NAMOBJ": "Bangunan Penampung Air", "ORDE01": 16011200, "ORDE02": 16011202, "JNSRSR": 46010000, "STSJRN": 1, "WADMPR": "Provinsi Jawa Tengah", "WADMKK": "Kabupaten Kendal", "REMARK": "Tidak Ada", "SBDATA": "Analisis RDTR, 2022" }, "geometry": { "type": "Point", "coordinates": [ 110.256391899134996, -6.917742981324977, 0.0 ] } },
{ "type": "Feature", "properties": { "OBJECTID": 2, "NAMOBJ": "Sumur Pompa", "ORDE01": 16012200, "ORDE02": 16012200, "JNSRSR": 46010000, "STSJRN": 1, "WADMPR": "Provinsi Jawa Tengah", "WADMKK": "Kabupaten Kendal", "REMARK": "Tidak Ada", "SBDATA": "Analisis RDTR, 2022" }, "geometry": { "type": "Point", "coordinates": [ 110.255758633887524, -6.970771743937519, 0.0 ] } },
{ "type": "Feature", "properties": { "OBJECTID": 3, "NAMOBJ": "Instalasi Produksi", "ORDE01": 16011200, "ORDE02": 16011201, "JNSRSR": 46010000, "STSJRN": 3, "WADMPR": "Provinsi Jawa Tengah", "WADMKK": "Kabupaten Kendal", "REMARK": "Water Treatment Plant (WTP)", "SBDATA": "Masterplan Kawasan Industri Kendal, 2021" }, "geometry": { "type": "Point", "coordinates": [ 110.262602127809998, -6.92161526947001, 0.0 ] } },
{ "type": "Feature", "properties": { "OBJECTID": 6, "NAMOBJ": "Sumur Dangkal", "ORDE01": 16012100, "ORDE02": 16012100, "JNSRSR": 46010000, "STSJRN": 3, "WADMPR": "Provinsi Jawa Tengah", "WADMKK": "Kabupaten Kendal", "REMARK": "Tidak Ada", "SBDATA": "Peraturan Daerah Kabupaten Kendal No 1 Tahun 2020 tentang Perubahan Atas Peraturan Daerah Kabupaten Kendal No 20 Tahun 2011 Tentang Rencana Tata Ruang Wilayah Kabupaten Kendal Tahun 2011-2031" }, "geometry": { "type": "Point", "coordinates": [ 110.256106506610024, -6.941099317372505, 0.0 ] } },
{ "type": "Feature", "properties": { "OBJECTID": 7, "NAMOBJ": "Sumur Dangkal", "ORDE01": 16012100, "ORDE02": 16012100, "JNSRSR": 46010000, "STSJRN": 3, "WADMPR": "Provinsi Jawa Tengah", "WADMKK": "Kabupaten Kendal", "REMARK": "Tidak Ada", "SBDATA": "Peraturan Daerah Kabupaten Kendal No 1 Tahun 2020 tentang Perubahan Atas Peraturan Daerah Kabupaten Kendal No 20 Tahun 2011 Tentang Rencana Tata Ruang Wilayah Kabupaten Kendal Tahun 2011-2031" }, "geometry": { "type": "Point", "coordinates": [ 110.254765442387509, -6.954954585685016, 0.0 ] } }
]
}
